meetuplib/__init__.py
meetuplib-0.25.dist-info/DESCRIPTION.rst
meetuplib-0.25.dist-info/METADATA
meetuplib-0.25.dist-info/RECORD
meetuplib-0.25.dist-info/WHEEL
meetuplib-0.25.dist-info/metadata.json
meetuplib-0.25.dist-info/top_level.txt
