Metadata-Version: 2.0
Name: meetuplib
Version: 0.25
Summary: Meetup API library
Home-page: http://github.com/michalzylinski/meetuplib
Author: Michal Zylinski
Author-email: michal.zylinski@gmail.com
License: Apache
Platform: UNKNOWN
